{"nodes": [{"id": "c_workspace_ai_lead_ai_lead_scratch_run_graphify_py", "label": "run_graphify.py", "file_type": "code", "source_file": "scratch/run_graphify.py", "source_location": "L1"}, {"id": "c_workspace_ai_lead_ai_lead_scratch_run_graphify_main", "label": "main()", "file_type": "code", "source_file": "scratch/run_graphify.py", "source_location": "L6", "_callable": true}], "edges": [{"source": "c_workspace_ai_lead_ai_lead_scratch_run_graphify_py", "target": "os", "relation": "imports", "context": "import", "confidence": "EXTRACTED", "source_file": "scratch/run_graphify.py", "source_location": "L1", "weight": 1.0}, {"source": "c_workspace_ai_lead_ai_lead_scratch_run_graphify_py", "target": "shutil", "relation": "imports", "context": "import", "confidence": "EXTRACTED", "source_file": "scratch/run_graphify.py", "source_location": "L2", "weight": 1.0}, {"source": "c_workspace_ai_lead_ai_lead_scratch_run_graphify_py", "target": "subprocess", "relation": "imports", "context": "import", "confidence": "EXTRACTED", "source_file": "scratch/run_graphify.py", "source_location": "L3", "weight": 1.0}, {"source": "c_workspace_ai_lead_ai_lead_scratch_run_graphify_py", "target": "pathlib", "relation": "imports_from", "context": "import", "confidence": "EXTRACTED", "source_file": "scratch/run_graphify.py", "source_location": "L4", "weight": 1.0}, {"source": "c_workspace_ai_lead_ai_lead_scratch_run_graphify_py", "target": "c_workspace_ai_lead_ai_lead_scratch_run_graphify_main", "relation": "contains", "confidence": "EXTRACTED", "source_file": "scratch/run_graphify.py", "source_location": "L6", "weight": 1.0}], "raw_calls": [{"caller_nid": "c_workspace_ai_lead_ai_lead_scratch_run_graphify_main", "callee": "Path", "is_member_call": false, "source_file": "C:\\Workspace\\AI-Lead\\AI-LEAD\\scratch\\run_graphify.py", "source_location": "L7", "receiver": null}, {"caller_nid": "c_workspace_ai_lead_ai_lead_scratch_run_graphify_main", "callee": "mkdir", "is_member_call": true, "source_file": "C:\\Workspace\\AI-Lead\\AI-LEAD\\scratch\\run_graphify.py", "source_location": "L9", "receiver": "temp_dir"}, {"caller_nid": "c_workspace_ai_lead_ai_lead_scratch_run_graphify_main", "callee": "walk", "is_member_call": true, "source_file": "C:\\Workspace\\AI-Lead\\AI-LEAD\\scratch\\run_graphify.py", "source_location": "L14", "receiver": "os"}, {"caller_nid": "c_workspace_ai_lead_ai_lead_scratch_run_graphify_main", "callee": "remove", "is_member_call": true, "source_file": "C:\\Workspace\\AI-Lead\\AI-LEAD\\scratch\\run_graphify.py", "source_location": "L17", "receiver": "dirs"}, {"caller_nid": "c_workspace_ai_lead_ai_lead_scratch_run_graphify_main", "callee": "remove", "is_member_call": true, "source_file": "C:\\Workspace\\AI-Lead\\AI-LEAD\\scratch\\run_graphify.py", "source_location": "L19", "receiver": "dirs"}, {"caller_nid": "c_workspace_ai_lead_ai_lead_scratch_run_graphify_main", "callee": "Path", "is_member_call": false, "source_file": "C:\\Workspace\\AI-Lead\\AI-LEAD\\scratch\\run_graphify.py", "source_location": "L22", "receiver": null}, {"caller_nid": "c_workspace_ai_lead_ai_lead_scratch_run_graphify_main", "callee": "relative_to", "is_member_call": true, "source_file": "C:\\Workspace\\AI-Lead\\AI-LEAD\\scratch\\run_graphify.py", "source_location": "L25", "receiver": "file_path"}, {"caller_nid": "c_workspace_ai_lead_ai_lead_scratch_run_graphify_main", "callee": "replace", "is_member_call": true, "source_file": "C:\\Workspace\\AI-Lead\\AI-LEAD\\scratch\\run_graphify.py", "source_location": "L26", "receiver": null}, {"caller_nid": "c_workspace_ai_lead_ai_lead_scratch_run_graphify_main", "callee": "move", "is_member_call": true, "source_file": "C:\\Workspace\\AI-Lead\\AI-LEAD\\scratch\\run_graphify.py", "source_location": "L29", "receiver": "shutil"}, {"caller_nid": "c_workspace_ai_lead_ai_lead_scratch_run_graphify_main", "callee": "append", "is_member_call": true, "source_file": "C:\\Workspace\\AI-Lead\\AI-LEAD\\scratch\\run_graphify.py", "source_location": "L30", "receiver": "moved_files"}, {"caller_nid": "c_workspace_ai_lead_ai_lead_scratch_run_graphify_main", "callee": "run", "is_member_call": true, "source_file": "C:\\Workspace\\AI-Lead\\AI-LEAD\\scratch\\run_graphify.py", "source_location": "L36", "receiver": "subprocess"}, {"caller_nid": "c_workspace_ai_lead_ai_lead_scratch_run_graphify_main", "callee": "exists", "is_member_call": true, "source_file": "C:\\Workspace\\AI-Lead\\AI-LEAD\\scratch\\run_graphify.py", "source_location": "L44", "receiver": "src"}, {"caller_nid": "c_workspace_ai_lead_ai_lead_scratch_run_graphify_main", "callee": "relative_to", "is_member_call": true, "source_file": "C:\\Workspace\\AI-Lead\\AI-LEAD\\scratch\\run_graphify.py", "source_location": "L45", "receiver": "dest"}, {"caller_nid": "c_workspace_ai_lead_ai_lead_scratch_run_graphify_main", "callee": "move", "is_member_call": true, "source_file": "C:\\Workspace\\AI-Lead\\AI-LEAD\\scratch\\run_graphify.py", "source_location": "L46", "receiver": "shutil"}, {"caller_nid": "c_workspace_ai_lead_ai_lead_scratch_run_graphify_main", "callee": "exists", "is_member_call": true, "source_file": "C:\\Workspace\\AI-Lead\\AI-LEAD\\scratch\\run_graphify.py", "source_location": "L49", "receiver": "temp_dir"}, {"caller_nid": "c_workspace_ai_lead_ai_lead_scratch_run_graphify_main", "callee": "listdir", "is_member_call": true, "source_file": "C:\\Workspace\\AI-Lead\\AI-LEAD\\scratch\\run_graphify.py", "source_location": "L49", "receiver": "os"}, {"caller_nid": "c_workspace_ai_lead_ai_lead_scratch_run_graphify_main", "callee": "rmdir", "is_member_call": true, "source_file": "C:\\Workspace\\AI-Lead\\AI-LEAD\\scratch\\run_graphify.py", "source_location": "L50", "receiver": "temp_dir"}]}